{
  "/general/getting-started-3d": [],
  "/general/finding-grain": [
    {
      "title": "Grain in Lens Studio",
      "path": "/lens-studio/grain"
    }
  ],
  "/lens-studio/freckles": [
    {
      "title": "Grain in Lens Studio",
      "path": "/lens-studio/grain"
    },
    {
      "title": "Kira Kira/Bling effect in Lens Studio",
      "path": "/lens-studio/kira-kira"
    }
  ],
  "/lens-studio/kira-kira": [
    {
      "title": "Grain in Lens Studio",
      "path": "/lens-studio/grain"
    },
    {
      "title": "Freckles in Lens Studio",
      "path": "/lens-studio/freckles"
    }
  ],
  "/lens-studio/grain": [
    {
      "title": "Finding grain textures",
      "path": "/general/finding-grain"
    },
    {
      "title": "Kira Kira/Bling effect in Lens Studio",
      "path": "/lens-studio/kira-kira"
    },
    {
      "title": "Freckles in Lens Studio",
      "path": "/lens-studio/freckles"
    }
  ],
  "/filters/2020-halloween-instagram": [
    {
      "title": "10 Incredible Snapchat Filters for Halloween 2020",
      "path": "/filters/2020-halloween-snapchat"
    }
  ],
  "/filters/2020-halloween-snapchat": [
    {
      "title": "10 Delightful Instagram Filters for Halloween 2020",
      "path": "/filters/2020-halloween-instagram"
    }
  ]
}
